telegramid/__init__.py
telegramid/main.py
telegramid-1.0.0.dist-info/LICENSE
telegramid-1.0.0.dist-info/METADATA
telegramid-1.0.0.dist-info/WHEEL
telegramid-1.0.0.dist-info/entry_points.txt
telegramid-1.0.0.dist-info/top_level.txt
telegramid-1.0.0.dist-info/RECORD
