Metadata-Version: 2.1
Name: telegramid
Version: 1.0.0
Summary: A package to fetch Telegram group chat ID, user ID, username, and message info
Home-page: https://github.com/ByteBreach/telegramid
Author: Fidal
Author-email: mrfidal@proton.me
Classifier: Programming Language :: Python :: 3
Classifier: License :: OSI Approved :: MIT License
Classifier: Operating System :: OS Independent
Requires-Python: >=3.6
License-File: LICENSE
Requires-Dist: requests
